carlos/__init__.py
carlos/_optional.py
carlos/_version.py
carlos/bundled_db.py
carlos/config.py
carlos/database.py
carlos/generative_prompts.py
carlos/index.py
carlos/retrieve.py
carlos/types.py
carlos/data/metrics_database.parquet
carlos-0.0.3.dist-info/licenses/LICENSE
carlos-0.0.3.dist-info/METADATA
carlos-0.0.3.dist-info/WHEEL
carlos-0.0.3.dist-info/top_level.txt
carlos-0.0.3.dist-info/RECORD
