Metadata-Version: 2.4
Name: carlos
Version: 0.0.3
Summary: GPU-based indexing and retrieval pipeline for LoRAs
Author: Shahar Sarfaty
License:                                  Apache License
Project-URL: Homepage, https://shahar-sarfaty.github.io/CARLoS/
Project-URL: Repository, https://github.com/shahar-sarfaty/CARLoS
Project-URL: Issues, https://github.com/shahar-sarfaty/CARLoS/issues
Keywords: retrieval,pytorch,gpu,indexing,LoRAs
Classifier: Programming Language :: Python :: 3
Classifier: Programming Language :: Python :: 3.9
Classifier: License :: OSI Approved :: MIT License
Requires-Python: <3.10,>=3.9
License-File: LICENSE
Requires-Dist: numpy==1.23.5
Requires-Dist: pandas==2.1.4
Requires-Dist: pyarrow==17.0.0
Provides-Extra: dev
Requires-Dist: pytest==8.3.4; extra == "dev"
Dynamic: license-file
